llama_ctrl/__init__.py
llama_ctrl/config.py
llama_ctrl/core.py
llama_ctrl-0.1.0.dist-info/METADATA
llama_ctrl-0.1.0.dist-info/WHEEL
llama_ctrl-0.1.0.dist-info/entry_points.txt
llama_ctrl-0.1.0.dist-info/licenses/LICENSE
llama_ctrl-0.1.0.dist-info/RECORD
